{"GlobalPropertiesHash":"2ilJ2M8+ZdH0swl4cXFj9Ji8kay0R08ISE/fEc+OL0o=","FingerprintPatternsHash":"8ZRc1sGeVrPBx4lD717BgRaQekyh78QKV9SKsdt638U=","PropertyOverridesHash":"8ZRc1sGeVrPBx4lD717BgRaQekyh78QKV9SKsdt638U=","InputHashes":["19IAiAtbD/vKmyIbqN0yxbuf\u002BS/st12\u002Be8qWBEPQG8s="],"CachedAssets":{"19IAiAtbD/vKmyIbqN0yxbuf\u002BS/st12\u002Be8qWBEPQG8s=":{"Identity":"C:\\Users\\acer\\Documents\\Aps\\AspNetWeek1.Api\\obj\\Debug\\net10.0\\compressed\\m3c7tgts3v-{0}-du6mxie0b3-du6mxie0b3.gz","SourceId":"AspNetWeek1.Api","SourceType":"Discovered","ContentRoot":"C:\\Users\\acer\\Documents\\Aps\\AspNetWeek1.Api\\obj\\Debug\\net10.0\\compressed\\","BasePath":"/","RelativePath":"hello#[.{fingerprint=du6mxie0b3}]?.txt.gz","AssetKind":"All","AssetMode":"All","AssetRole":"Alternative","AssetMergeBehavior":null,"AssetMergeSource":"","RelatedAsset":"C:\\Users\\acer\\Documents\\Aps\\AspNetWeek1.Api\\wwwroot\\hello.txt","AssetTraitName":"Content-Encoding","AssetTraitValue":"gzip","Fingerprint":"oxtuvk8iil","Integrity":"DEJ0X6RUpt9Pa5i3ZNAy6o2BIgZxDK7NSEskpiI1HFw=","CopyToOutputDirectory":"Never","CopyToPublishDirectory":"PreserveNewest","OriginalItemSpec":"C:\\Users\\acer\\Documents\\Aps\\AspNetWeek1.Api\\wwwroot\\hello.txt","FileLength":57,"LastWriteTime":"2026-04-17T03:47:58.1702296+00:00"}},"CachedCopyCandidates":{}}